LICENSE
MANIFEST.in
README.md
requirements.txt
setup.cfg
setup.py
safe2pay/__init__.py
safe2pay.egg-info/PKG-INFO
safe2pay.egg-info/SOURCES.txt
safe2pay.egg-info/dependency_links.txt
safe2pay.egg-info/requires.txt
safe2pay.egg-info/top_level.txt
safe2pay/entities/__init__.py
safe2pay/entities/accountresponse.py
safe2pay/entities/accounttype.py
safe2pay/entities/address.py
safe2pay/entities/addresstransactionresponse.py
safe2pay/entities/anticipation.py
safe2pay/entities/bank.py
safe2pay/entities/bankdata.py
safe2pay/entities/bankslip.py
safe2pay/entities/bankslip_response.py
safe2pay/entities/boleto.py
safe2pay/entities/carnet.py
safe2pay/entities/carnetasync.py
safe2pay/entities/chargeback.py
safe2pay/entities/checkingaccount.py
safe2pay/entities/city.py
safe2pay/entities/creditcard.py
safe2pay/entities/customer.py
safe2pay/entities/customertransactionresponse.py
safe2pay/entities/deposit.py
safe2pay/entities/effectiveness.py
safe2pay/entities/erroresponse.py
safe2pay/entities/extract.py
safe2pay/entities/installments.py
safe2pay/entities/installmentvalue.py
safe2pay/entities/integration.py
safe2pay/entities/marketplace.py
safe2pay/entities/marketplacelistresponse.py
safe2pay/entities/marketplaceobjects.py
safe2pay/entities/merchantaccount.py
safe2pay/entities/merchantbankdata.py
safe2pay/entities/merchantpayment.py
safe2pay/entities/merchantpayment_response.py
safe2pay/entities/merchantpaymentdate.py
safe2pay/entities/merchantsplit.py
safe2pay/entities/merchanttype.py
safe2pay/entities/payment.py
safe2pay/entities/paymentmethod.py
safe2pay/entities/paymentobject.py
safe2pay/entities/paymentoption.py
safe2pay/entities/pix.py
safe2pay/entities/plan.py
safe2pay/entities/plandataresponse.py
safe2pay/entities/planfrequence.py
safe2pay/entities/planresponse.py
safe2pay/entities/plansubscription.py
safe2pay/entities/plansubscriptioncancelresponse.py
safe2pay/entities/product.py
safe2pay/entities/responsedetail.py
safe2pay/entities/responsedetail_account.py
safe2pay/entities/responsedetailtransactionget.py
safe2pay/entities/singlesale.py
safe2pay/entities/split.py
safe2pay/entities/staticpix.py
safe2pay/entities/tax.py
