Metadata-Version: 2.1
Name: safe2pay
Version: 0.0.16
Summary: SDK Python3 para Integração com Safe2Pay
Home-page: https://github.com/robertons/safe2pay
Author: Roberto Neves
Author-email: robertonsilva@gmail.com
License: MIT
Keywords: safe2pay,pagamento,cartão de crédito,boleto,pix,pagamentos,transações,payment,payments,credit-card
Classifier: Development Status :: 5 - Production/Stable
Classifier: Environment :: Web Environment
Classifier: Intended Audience :: Developers
Classifier: Natural Language :: Portuguese (Brazilian)
Classifier: Operating System :: OS Independent
Classifier: License :: OSI Approved :: MIT License
Classifier: Programming Language :: Python :: 3
Classifier: Programming Language :: Python :: Implementation :: PyPy
Classifier: Topic :: Internet
Classifier: Topic :: Office/Business
Classifier: Topic :: Utilities
License-File: LICENSE
